README.rst
setup.cfg
setup.py
firms/__init__.py
firms/command_line.py
firms/graders.py
firms/models.py
firms/sql_irsystems.py
firms/stemmers.py
firms/test_stemmers.py
firms/tokenizers.py
firms.egg-info/PKG-INFO
firms.egg-info/SOURCES.txt
firms.egg-info/dependency_links.txt
firms.egg-info/entry_points.txt
firms.egg-info/requires.txt
firms.egg-info/top_level.txt