Metadata-Version: 1.2
Name: firms
Version: 0.0.10
Summary: Fuzzy Information Retrieval for Musical Scores
Home-page: https://github.com/axiomabsolute/cs410-information-retrieval
Author: Devon Terrell
Author-email: devon@axioms.me
License: MIT
Download-URL: https://github.com/axiomabsolute/cs410-information-retrieval/archive/0.0.10.tar.gz
Platform: UNKNOWN
Requires-Python: >=3
